pybpf/__init__.py
pybpf/bpf.py
pybpf/bpf_header.py
pybpf/dimension.py
pybpf/exceptions.py
pybpf/ulem.py
pybpf-1.0.2.dist-info/LICENSE
pybpf-1.0.2.dist-info/METADATA
pybpf-1.0.2.dist-info/WHEEL
pybpf-1.0.2.dist-info/top_level.txt
pybpf-1.0.2.dist-info/RECORD
