Metadata-Version: 2.1
Name: pybpf
Version: 1.0.2
Summary: A python library to read bpf files
Author-email: El Mehdi SLAOUI <mehdislaoui14@gmail.com>
Classifier: Programming Language :: Python :: 3
Classifier: License :: OSI Approved :: MIT License
Classifier: Operating System :: OS Independent
Requires-Python: >=3.6
License-File: LICENSE
Requires-Dist: numpy >=1.25.2
